filterhero/__init__.py
filterhero/filter_engine.py
filterhero/filterhero.py
filterhero/myllmservice.py
filterhero/prompts.py
filterhero/schemas.py
filterhero/utils.py
filterhero-0.0.1.dist-info/METADATA
filterhero-0.0.1.dist-info/WHEEL
filterhero-0.0.1.dist-info/top_level.txt
filterhero-0.0.1.dist-info/RECORD
